ThreadShare/__init__.py
ThreadShare/managed_thread.py
ThreadShare/monitor.py
ThreadShare/task.py
ThreadShare/thread_manager.py
ThreadShare-0.2.dist-info/LICENSE
ThreadShare-0.2.dist-info/METADATA
ThreadShare-0.2.dist-info/WHEEL
ThreadShare-0.2.dist-info/top_level.txt
ThreadShare-0.2.dist-info/RECORD
