Metadata-Version: 2.1
Name: ThreadShare
Version: 0.2
Summary: A Python library to maximise CPU usage by smartly sharing threads among multiple functions.
Home-page: https://github.com/benjamincham/ThreadShare
Author: Benjamin Cham
Author-email: benjaminchamwb@gmail.com
Project-URL: Bug Tracker, https://github.com/benjamincham/ThreadShare/issues
Project-URL: Changelog, https://github.com/benjamincham/ThreadShare/releases
Classifier: Programming Language :: Python :: 3
Classifier: License :: OSI Approved :: BSD License
Classifier: Intended Audience :: Developers
License-File: LICENSE
Requires-Dist: psutil
